spotifyrehydrator/__init__.py
spotifyrehydrator/utils.py
spotifyrehydrator-0.2.0.dist-info/LICENSE
spotifyrehydrator-0.2.0.dist-info/METADATA
spotifyrehydrator-0.2.0.dist-info/WHEEL
spotifyrehydrator-0.2.0.dist-info/top_level.txt
spotifyrehydrator-0.2.0.dist-info/RECORD
