Metadata-Version: 2.1
Name: spotifyrehydrator
Version: 0.2.0
Summary: A convenience package for creating datasets of track features from self-requested Spotify data.
Home-page: https://github.com/DynamicGenetics/Spotify-Rehydrator
Author: Nina Di Cara
Author-email: ninadicara@gmail.com
Project-URL: Bug Tracker, https://github.com/DynamicGenetics/Spotify-Rehydrator/issues
Classifier: Programming Language :: Python :: 3
Classifier: License :: OSI Approved :: GNU General Public License v3 (GPLv3)
Classifier: Operating System :: OS Independent
Requires-Python: >=3.6
License-File: LICENSE
Requires-Dist: spotipy >=2.16
Requires-Dist: alive-progress >=1.6
Requires-Dist: pandas >=1.2
Requires-Dist: simplejson >=3.17
